LICENSE
LICENSE_kernprof.txt
README.md
setup.py
pytorch_memlab/__init__.py
pytorch_memlab/courtesy.py
pytorch_memlab/mem_reporter.py
pytorch_memlab/utils.py
pytorch_memlab.egg-info/PKG-INFO
pytorch_memlab.egg-info/SOURCES.txt
pytorch_memlab.egg-info/dependency_links.txt
pytorch_memlab.egg-info/requires.txt
pytorch_memlab.egg-info/top_level.txt
pytorch_memlab.egg-info/zip-safe
pytorch_memlab/line_profiler/__init__.py
pytorch_memlab/line_profiler/extension.py
pytorch_memlab/line_profiler/line_profiler.py
pytorch_memlab/line_profiler/line_records.py
pytorch_memlab/line_profiler/profile.py
test/__init__.py
test/test_courtesy.py
test/test_line_profiler.py
test/test_mem_reporter.py