Metadata-Version: 2.1
Name: pytorch-memlab
Version: 0.3.0
Summary: A lab to do simple and accurate memory experiments on pytorch
Home-page: https://github.com/Stonesjtu/pytorch_memlab
Author: Kaiyu Shi
Author-email: skyisno.1@gmail.com
License: MIT
Keywords: pytorch memory profile
Platform: UNKNOWN
Classifier: Programming Language :: Python
Classifier: Topic :: Software Development :: Libraries :: Python Modules
Provides-Extra: ipython
Provides-Extra: test
License-File: LICENSE
License-File: LICENSE_kernprof.txt
